CHANGELOG.txt
README.txt
setup.py
DevGuide/current/CooprDevGuide-docinfo.xml
DevGuide/current/CooprDevGuide.txt
DevGuide/current/Makefile
DevGuide/current/Makefile.local
DevGuide/current/asciidoc.conf
DevGuide/current/html.conf
DevGuide/current/include_anchors.py
DevGuide/current/examples/coopr_api.txt
DevGuide/current/examples/example1.py
DevGuide/current/examples/example1.txt
DevGuide/current/examples/example2.py
DevGuide/current/examples/example2.txt
DevGuide/current/examples/example3.py
DevGuide/current/examples/example3.txt
DevGuide/current/examples/example4.py
DevGuide/current/examples/example4.txt
DevGuide/current/examples/example5.py
DevGuide/current/examples/example5.txt
GettingStarted/SAND-2012-1572P/CooprGettingStarted.txt
GettingStarted/SAND-2012-1572P/DOE_logo.eps
GettingStarted/SAND-2012-1572P/DOE_logo.png
GettingStarted/SAND-2012-1572P/Makefile
GettingStarted/SAND-2012-1572P/Makefile.local
GettingStarted/SAND-2012-1572P/SNL_logo.eps
GettingStarted/SAND-2012-1572P/SNL_logo.png
GettingStarted/SAND-2012-1572P/appendix.txt
GettingStarted/SAND-2012-1572P/asciidoc.conf
GettingStarted/SAND-2012-1572P/blackbox.txt
GettingStarted/SAND-2012-1572P/book-docinfo.xml
GettingStarted/SAND-2012-1572P/book-end.txt
GettingStarted/SAND-2012-1572P/book-start.txt
GettingStarted/SAND-2012-1572P/catalog.xml
GettingStarted/SAND-2012-1572P/example.txt
GettingStarted/SAND-2012-1572P/html.conf
GettingStarted/SAND-2012-1572P/include_anchors.py
GettingStarted/SAND-2012-1572P/intro.txt
GettingStarted/SAND-2012-1572P/pyomo.txt
GettingStarted/SAND-2012-1572P/pysp.txt
GettingStarted/SAND-2012-1572P/reference.txt
GettingStarted/SAND-2012-1572P/scripts.txt
GettingStarted/SAND-2012-1572P/solvers.txt
GettingStarted/SAND-2012-1572P/OLD/intro-ch.tex
GettingStarted/SAND-2012-1572P/OLD/overview-ch.tex
GettingStarted/SAND-2012-1572P/epub/README
GettingStarted/SAND-2012-1572P/epub/docbook.xsl
GettingStarted/SAND-2012-1572P/epub/bin/dbtoepub
coopr.doc.egg-info/PKG-INFO
coopr.doc.egg-info/SOURCES.txt
coopr.doc.egg-info/dependency_links.txt
coopr.doc.egg-info/namespace_packages.txt
coopr.doc.egg-info/top_level.txt
